{
  "runId": "8f4bf20d-77b2-486b-8032-b044dab97476",
  "topic": "Storing values in variables and using basic data types",
  "options": {
    "language": "python",
    "difficulty": "beginner",
    "targetDuration": 5
  },
  "startedAt": "2026-04-17T12:41:52.703Z",
  "status": "completed",
  "steps": [
    {
      "agent": "Planner",
      "action": "generate",
      "round": 1,
      "startedAt": "2026-04-17T12:41:52.703Z",
      "completedAt": "2026-04-17T12:42:10.473Z"
    },
    {
      "agent": "PlanReviewer",
      "action": "review",
      "round": 1,
      "startedAt": "2026-04-17T12:42:10.473Z",
      "approved": false,
      "completedAt": "2026-04-17T12:42:33.401Z"
    },
    {
      "agent": "Planner",
      "action": "revise",
      "round": 2,
      "startedAt": "2026-04-17T12:42:33.402Z",
      "completedAt": "2026-04-17T12:42:49.107Z"
    },
    {
      "agent": "PlanReviewer",
      "action": "review",
      "round": 2,
      "startedAt": "2026-04-17T12:42:49.107Z",
      "approved": true,
      "completedAt": "2026-04-17T12:43:00.416Z"
    },
    {
      "agent": "Scripter",
      "action": "generate",
      "round": 1,
      "startedAt": "2026-04-17T12:43:00.416Z",
      "completedAt": "2026-04-17T12:43:37.619Z"
    },
    {
      "agent": "ScriptReviewer",
      "action": "review",
      "round": 1,
      "startedAt": "2026-04-17T12:43:37.620Z",
      "approved": false,
      "completedAt": "2026-04-17T12:44:10.667Z"
    },
    {
      "agent": "Scripter",
      "action": "revise",
      "round": 2,
      "startedAt": "2026-04-17T12:44:10.667Z",
      "completedAt": "2026-04-17T12:44:44.686Z"
    },
    {
      "agent": "ScriptReviewer",
      "action": "review",
      "round": 2,
      "startedAt": "2026-04-17T12:44:44.686Z",
      "approved": true,
      "completedAt": "2026-04-17T12:45:03.203Z"
    },
    {
      "agent": "Validator",
      "action": "validateAll",
      "round": 1,
      "startedAt": "2026-04-17T12:45:03.203Z",
      "completedAt": "2026-04-17T12:45:50.697Z"
    },
    {
      "agent": "TTS",
      "action": "generateAll",
      "round": 1,
      "startedAt": "2026-04-17T12:45:50.697Z",
      "completedAt": "2026-04-17T12:46:36.805Z"
    },
    {
      "agent": "Assembler",
      "action": "assemble",
      "round": 1,
      "startedAt": "2026-04-17T12:46:36.805Z",
      "completedAt": "2026-04-17T12:46:36.805Z"
    },
    {
      "agent": "FinalReviewer",
      "action": "review",
      "round": 1,
      "startedAt": "2026-04-17T12:46:36.805Z",
      "approved": true,
      "completedAt": "2026-04-17T12:46:55.628Z"
    }
  ],
  "totalLLMCalls": 12,
  "totalLLMTokens": {
    "input": 0,
    "output": 0
  },
  "completedAt": "2026-04-17T12:46:55.628Z"
}